COPYING.LIB.txt
COPYING.txt
MANIFEST.in
README.rst
requirements.txt
setup.py
IntelliCoder.egg-info/PKG-INFO
IntelliCoder.egg-info/SOURCES.txt
IntelliCoder.egg-info/dependency_links.txt
IntelliCoder.egg-info/entry_points.txt
IntelliCoder.egg-info/requires.txt
IntelliCoder.egg-info/top_level.txt
intellicoder/__init__.py
intellicoder/__main__.py
intellicoder/builders.py
intellicoder/converters.py
intellicoder/database.py
intellicoder/init.py
intellicoder/linux.db
intellicoder/main.py
intellicoder/sources.py
intellicoder/synthesizers.py
intellicoder/transformers.py
intellicoder/utils.py
intellicoder/version.txt
intellicoder/windows.db
intellicoder/executables/__init__.py
intellicoder/executables/elf.py
intellicoder/executables/executables.py
intellicoder/executables/pe.py
intellicoder/intellisense/__init__.py
intellicoder/intellisense/database.py
intellicoder/intellisense/formatters.py
intellicoder/intellisense/sanitizers.py
intellicoder/msbuild/__init__.py
intellicoder/msbuild/builders.py
intellicoder/msbuild/locators.py
recipes/linux/exec/32.bin
recipes/linux/exec/64.bin
recipes/linux/exec/exec.c
recipes/linux/fork/32.bin
recipes/linux/fork/64.bin
recipes/linux/fork/fork.c
recipes/linux/read/32.bin
recipes/linux/read/64.bin
recipes/linux/read/read.c
recipes/linux/wget/32.bin
recipes/linux/wget/wget.c
recipes/linux/write/32.bin
recipes/linux/write/64.bin
recipes/linux/write/write.c
recipes/windows/bindshell/bindshell.c
recipes/windows/bindshell/sockbind.c
recipes/windows/createprocess/createprocess.c
recipes/windows/crt/crt.c
recipes/windows/dir/dir.c
recipes/windows/download_and_exec/down.c
recipes/windows/download_and_exec/test.txt
recipes/windows/download_and_exec/x64-pointer-truncation.asm
recipes/windows/error/a.c
recipes/windows/error/libwinerror.c
recipes/windows/error/libwinerror.h
recipes/windows/error/printf.asm
recipes/windows/messagebox/messagebox.c
recipes/windows/reverseshell/reverseshell.c
recipes/windows/reverseshell/sockrev.c
recipes/windows/winexec/winexec.c
scripts/import.sh
static/README.rst
static/hash.c
static/windows.h
static/include/common.h
static/include/string.h
static/include/structs.h
static/syscall/Makefile
static/syscall/syscall.c
