Metadata-Version: 1.1
Name: IntelliCoder
Version: 0.5.2
Summary: Shellcoding Helper
Home-page: https://github.com/NoviceLive/intellicoder
Author: Gu Zhengxiong
Author-email: rectigu@gmail.com
License: GPL
Keywords: Shellcode,Binary
Platform: UNKNOWN
Classifier: Development Status :: 4 - Beta
Classifier: Environment :: Console
Classifier: Intended Audience :: Developers
Classifier: Intended Audience :: Information Technology
Classifier: License :: OSI Approved :: GNU General Public License v3 or later (GPLv3+)
Classifier: Natural Language :: English
Classifier: Operating System :: OS Independent
Classifier: Programming Language :: Python :: 2.7
Classifier: Programming Language :: Python :: 3.4
Classifier: Programming Language :: Python :: 3.5
